[
    {
        "idCompra": "15814903900022024",
        "numeroControlePNCP": "10830301000104-1-000031/2024",
        "anoCompraPncp": 2024,
        "sequencialCompraPncp": 31,
        "orgaoEntidadeCnpj": "10830301000104",
        "orgaoSubrogadoCnpj": null,
        "codigoOrgao": 60919,
        "orgaoEntidadeRazaoSocial": "INSTITUTO FEDERAL DE EDUCACAO, CIENCIA E TECNOLOGIA DO SERTAO PERNAMBUCANO",
        "orgaoSubrogadoRazaoSocial": null,
        "orgaoEntidadeEsferaId": "F",
        "orgaoSubrogadoEsferaId": null,
        "orgaoEntidadePoderId": "E",
        "orgaoSubrogadoPoderId": null,
        "unidadeOrgaoCodigoUnidade": "158149",
        "unidadeSubrogadaCodigoUnidade": null,
        "unidadeOrgaoNomeUnidade": "INST.FED.EDUC.CIENC.E TEC.SERTãO PERNAMBUCANO",
        "unidadeSubrogadaNomeUnidade": null,
        "unidadeOrgaoUfSigla": "PE",
        "unidadeSubrogadaUfSigla": null,
        "unidadeOrgaoMunicipioNome": "PETROLINA",
        "unidade_subrogada_municipio_nome": null,
        "unidadeOrgaoCodigoIbge": 2611101,
        "unidadeSubrogadaCodigoIbge": null,
        "numeroCompra": "90002",
        "modalidadeIdPncp": 4,
        "codigoModalidade": 3,
        "modalidadeNome": "Concorrência - Eletrônica",
        "srp": false,
        "modoDisputaIdPncp": 3,
        "codigoModoDisputa": 3,
        "amparoLegalCodigoPncp": 2,
        "amparoLegalNome": "Lei 14.133/2021, Art. 28, II ",
        "amparoLegalDescricao": "concorrência: modalidade de licitação para contratação de bens e serviços especiais e de obras e serviços comuns e especiais de engenharia",
        "informacaoComplementar": " Para as respostas de esclarecimentos e impugnações deste edital acesse o link: https://cnetmobile.estaleiro.serpro.gov.br/comprasnet-web/public/landing?destino=quadro-informativo&compra=15814903900022024",
        "processo": "23302101339202417",
        "objetoCompra": "Contratação de empresa de engenharia responsável pela , Construção do Refeitório do Campus Salgueiro do IFSertãoPE.",
        "existeResultado": true,
        "orcamentoSigilosoCodigo": 1,
        "orcamentoSigilosoDescricao": "Compra sem sigilo",
        "situacaoCompraIdPncp": 1,
        "situacaoCompraNomePncp": "Divulgada no PNCP",
        "tipoInstrumentoConvocatorioCodigoPncp": 1,
        "tipoInstrumentoConvocatorioNome": "Edital",
        "modoDisputaNomePncp": "Aberto-Fechado",
        "valorTotalEstimado": 2034844.01,
        "valorTotalHomologado": 1526133.0075,
        "dataInclusaoPncp": "2024-10-31T07:02:14",
        "dataAtualizacaoPncp": "2024-10-31T07:02:14",
        "dataPublicacaoPncp": "2024-10-31T07:02:14",
        "dataAberturaPropostaPncp": "2024-10-31T08:00:00",
        "dataEncerramentoPropostaPncp": "2024-11-14T15:00:00",
        "contratacaoExcluida": false
    },
    {
        "idCompra": "15814903900012024",
        "numeroControlePNCP": "10830301000104-1-000030/2024",
        "anoCompraPncp": 2024,
        "sequencialCompraPncp": 30,
        "orgaoEntidadeCnpj": "10830301000104",
        "orgaoSubrogadoCnpj": null,
        "codigoOrgao": 60919,
        "orgaoEntidadeRazaoSocial": "INSTITUTO FEDERAL DE EDUCACAO, CIENCIA E TECNOLOGIA DO SERTAO PERNAMBUCANO",
        "orgaoSubrogadoRazaoSocial": null,
        "orgaoEntidadeEsferaId": "F",
        "orgaoSubrogadoEsferaId": null,
        "orgaoEntidadePoderId": "E",
        "orgaoSubrogadoPoderId": null,
        "unidadeOrgaoCodigoUnidade": "158149",
        "unidadeSubrogadaCodigoUnidade": null,
        "unidadeOrgaoNomeUnidade": "INST.FED.EDUC.CIENC.E TEC.SERTãO PERNAMBUCANO",
        "unidadeSubrogadaNomeUnidade": null,
        "unidadeOrgaoUfSigla": "PE",
        "unidadeSubrogadaUfSigla": null,
        "unidadeOrgaoMunicipioNome": "PETROLINA",
        "unidade_subrogada_municipio_nome": null,
        "unidadeOrgaoCodigoIbge": 2611101,
        "unidadeSubrogadaCodigoIbge": null,
        "numeroCompra": "90001",
        "modalidadeIdPncp": 4,
        "codigoModalidade": 3,
        "modalidadeNome": "Concorrência - Eletrônica",
        "srp": false,
        "modoDisputaIdPncp": 3,
        "codigoModoDisputa": 3,
        "amparoLegalCodigoPncp": 2,
        "amparoLegalNome": "Lei 14.133/2021, Art. 28, II ",
        "amparoLegalDescricao": "concorrência: modalidade de licitação para contratação de bens e serviços especiais e de obras e serviços comuns e especiais de engenharia",
        "informacaoComplementar": " Para as respostas de esclarecimentos e impugnações deste edital acesse o link: https://cnetmobile.estaleiro.serpro.gov.br/comprasnet-web/public/landing?destino=quadro-informativo&compra=15814903900012024",
        "processo": "23302101340202433",
        "objetoCompra": "Contratação de empresa de engenharia responsável pela Construção da Biblioteca dos Campi Floresta e Petrolina Zona Rural do IFSertãoPE.",
        "existeResultado": true,
        "orcamentoSigilosoCodigo": 1,
        "orcamentoSigilosoDescricao": "Compra sem sigilo",
        "situacaoCompraIdPncp": 1,
        "situacaoCompraNomePncp": "Divulgada no PNCP",
        "tipoInstrumentoConvocatorioCodigoPncp": 1,
        "tipoInstrumentoConvocatorioNome": "Edital",
        "modoDisputaNomePncp": "Aberto-Fechado",
        "valorTotalEstimado": 3381450.9,
        "valorTotalHomologado": 2585363.0173,
        "dataInclusaoPncp": "2024-10-31T07:01:18",
        "dataAtualizacaoPncp": "2024-10-31T07:01:18",
        "dataPublicacaoPncp": "2024-10-31T07:01:18",
        "dataAberturaPropostaPncp": "2024-10-31T09:00:00",
        "dataEncerramentoPropostaPncp": "2024-11-14T09:00:00",
        "contratacaoExcluida": false
    },
    {
        "idCompra": "15814903900032024",
        "numeroControlePNCP": "10830301000104-1-000032/2024",
        "anoCompraPncp": 2024,
        "sequencialCompraPncp": 32,
        "orgaoEntidadeCnpj": "10830301000104",
        "orgaoSubrogadoCnpj": null,
        "codigoOrgao": 60919,
        "orgaoEntidadeRazaoSocial": "INSTITUTO FEDERAL DE EDUCACAO, CIENCIA E TECNOLOGIA DO SERTAO PERNAMBUCANO",
        "orgaoSubrogadoRazaoSocial": null,
        "orgaoEntidadeEsferaId": "F",
        "orgaoSubrogadoEsferaId": null,
        "orgaoEntidadePoderId": "E",
        "orgaoSubrogadoPoderId": null,
        "unidadeOrgaoCodigoUnidade": "158149",
        "unidadeSubrogadaCodigoUnidade": null,
        "unidadeOrgaoNomeUnidade": "INST.FED.EDUC.CIENC.E TEC.SERTãO PERNAMBUCANO",
        "unidadeSubrogadaNomeUnidade": null,
        "unidadeOrgaoUfSigla": "PE",
        "unidadeSubrogadaUfSigla": null,
        "unidadeOrgaoMunicipioNome": "PETROLINA",
        "unidade_subrogada_municipio_nome": null,
        "unidadeOrgaoCodigoIbge": 2611101,
        "unidadeSubrogadaCodigoIbge": null,
        "numeroCompra": "90003",
        "modalidadeIdPncp": 4,
        "codigoModalidade": 3,
        "modalidadeNome": "Concorrência - Eletrônica",
        "srp": false,
        "modoDisputaIdPncp": 3,
        "codigoModoDisputa": 3,
        "amparoLegalCodigoPncp": 2,
        "amparoLegalNome": "Lei 14.133/2021, Art. 28, II ",
        "amparoLegalDescricao": "concorrência: modalidade de licitação para contratação de bens e serviços especiais e de obras e serviços comuns e especiais de engenharia",
        "informacaoComplementar": " Para as respostas de esclarecimentos e impugnações deste edital acesse o link: https://cnetmobile.estaleiro.serpro.gov.br/comprasnet-web/public/landing?destino=quadro-informativo&compra=15814903900032024",
        "processo": "23302101335202421",
        "objetoCompra": "Contratação de empresa de engenharia responsável pela, Construção da Sede da Reitoria do IFSertãoPE.",
        "existeResultado": true,
        "orcamentoSigilosoCodigo": 1,
        "orcamentoSigilosoDescricao": "Compra sem sigilo",
        "situacaoCompraIdPncp": 1,
        "situacaoCompraNomePncp": "Divulgada no PNCP",
        "tipoInstrumentoConvocatorioCodigoPncp": 1,
        "tipoInstrumentoConvocatorioNome": "Edital",
        "modoDisputaNomePncp": "Aberto-Fechado",
        "valorTotalEstimado": 12578525.09,
        "valorTotalHomologado": 9559679.0684,
        "dataInclusaoPncp": "2024-10-31T07:05:10",
        "dataAtualizacaoPncp": "2024-10-31T07:05:10",
        "dataPublicacaoPncp": "2024-10-31T07:05:10",
        "dataAberturaPropostaPncp": "2024-10-31T09:00:00",
        "dataEncerramentoPropostaPncp": "2024-11-18T09:30:00",
        "contratacaoExcluida": false
    }
]